{
    "Titolo": "Altri cinque casi in zona Tre sono a Piombino",
    "ID articolo": "139971389",
    "Testo": "<p><b>Sono cinque le persone contagiate dal Covid in tutta la nostra zona, in base ai dati forniti dall\u2019Azienda sanitaria Toscana Nordovest. Tre contagi sono stati rilevati a Piombino, uno a Campiglia Marittima e uno a San Vincenzo. Nell\u2019ambito della Societ\u00e0 della salute Valli Etrusche \u00e8 di 23 il totale dei nuovi positivi. Quanto alla campagna di vaccinazione, \u00e8 possibile seguirla in tempo reale sul portale regionale https:\/\/vaccinazioni.sanita.toscana.it. <\/b><br\/><br\/><\/p>",
    "URL": "2021\/03\/01\/news\/altri-cinque-casi-in-zona-tre-sono-a-piombino",
    "Abstract": "",
    "Autore": "",
    "Categorie": ""
}